pywikibase/__init__.py
pywikibase/about.py
pywikibase/claim.py
pywikibase/coordinate.py
pywikibase/exceptions.py
pywikibase/itempage.py
pywikibase/propertypage.py
pywikibase/wbproperty.py
pywikibase/wbquantity.py
pywikibase/wbtime.py
pywikibase/wikibasepage.py
pywikibase-0.0.5.dist-info/DESCRIPTION.rst
pywikibase-0.0.5.dist-info/METADATA
pywikibase-0.0.5.dist-info/RECORD
pywikibase-0.0.5.dist-info/WHEEL
pywikibase-0.0.5.dist-info/metadata.json
pywikibase-0.0.5.dist-info/top_level.txt
