Metadata-Version: 2.0
Name: pywikibase
Version: 0.0.5
Summary: Python package to handle Wikibase DataModel
Home-page: https://www.mediawiki.org/wiki/Pywikibot
Author: The Pywikibot team
Author-email: pywikibot@lists.wikimedia.org
License: MIT License
Platform: UNKNOWN
Classifier: License :: OSI Approved :: MIT License
Classifier: Development Status :: 3 - Alpha
Classifier: Operating System :: OS Independent
Classifier: Intended Audience :: Developers
Classifier: Environment :: Console
Classifier: Programming Language :: Python :: 2.7
Classifier: Programming Language :: Python :: 3.3
